contextr/__init__.py
contextr/cli.py
contextr/formatters.py
contextr/manager.py
contextr/profile.py
contextr/storage/__init__.py
contextr/storage/base.py
contextr/storage/json_storage.py
contextr/utils/__init__.py
contextr/utils/ignore_utils.py
contextr/utils/path_utils.py
contextr-1.2.0.dist-info/METADATA
contextr-1.2.0.dist-info/WHEEL
contextr-1.2.0.dist-info/entry_points.txt
contextr-1.2.0.dist-info/top_level.txt
contextr-1.2.0.dist-info/RECORD
