Metadata-Version: 2.4
Name: contextr
Version: 1.2.0
Summary: Share your codebase with LLMs - codebase export tool for AI conversations
Author-email: Nathan Luo <nathanluo13@gmail.com>
License: MIT
Project-URL: Homepage, https://github.com/nathan-luo/contextr
Project-URL: Bug Tracker, https://github.com/nathan-luo/contextr/issues
Keywords: llm,ai,codebase,clipboard,context
Requires-Python: >=3.12
Requires-Dist: prompt-toolkit>=3.0.48
Requires-Dist: pyperclip>=1.9.0
Requires-Dist: rich>=13.9.4
Requires-Dist: typer>=0.15.1
Provides-Extra: dev
Requires-Dist: ruff>=0.8.6; extra == "dev"
Requires-Dist: pyright>=1.1.389; extra == "dev"
Requires-Dist: pytest>=8.3.4; extra == "dev"
Requires-Dist: pytest-cov>=6.0.0; extra == "dev"
Requires-Dist: pytest-mock>=3.14.0; extra == "dev"
Requires-Dist: pre-commit>=4.0.1; extra == "dev"
